odoo8_addon_email_template_qweb-8.0.1.0.0.99.dev7-py2.7-nspkg.pth
odoo8_addon_email_template_qweb-8.0.1.0.0.99.dev7.dist-info/DESCRIPTION.rst
odoo8_addon_email_template_qweb-8.0.1.0.0.99.dev7.dist-info/METADATA
odoo8_addon_email_template_qweb-8.0.1.0.0.99.dev7.dist-info/RECORD
odoo8_addon_email_template_qweb-8.0.1.0.0.99.dev7.dist-info/WHEEL
odoo8_addon_email_template_qweb-8.0.1.0.0.99.dev7.dist-info/metadata.json
odoo8_addon_email_template_qweb-8.0.1.0.0.99.dev7.dist-info/namespace_packages.txt
odoo8_addon_email_template_qweb-8.0.1.0.0.99.dev7.dist-info/top_level.txt
odoo_addons/email_template_qweb/README.rst
odoo_addons/email_template_qweb/__init__.py
odoo_addons/email_template_qweb/__openerp__.py
odoo_addons/email_template_qweb/demo/email_template.xml
odoo_addons/email_template_qweb/demo/ir_ui_view.xml
odoo_addons/email_template_qweb/i18n/ca.po
odoo_addons/email_template_qweb/i18n/da.po
odoo_addons/email_template_qweb/i18n/de.po
odoo_addons/email_template_qweb/i18n/el_GR.po
odoo_addons/email_template_qweb/i18n/email_template_qweb.pot
odoo_addons/email_template_qweb/i18n/es.po
odoo_addons/email_template_qweb/i18n/es_CO.po
odoo_addons/email_template_qweb/i18n/fr.po
odoo_addons/email_template_qweb/i18n/pt_BR.po
odoo_addons/email_template_qweb/i18n/sl.po
odoo_addons/email_template_qweb/models/__init__.py
odoo_addons/email_template_qweb/models/email_template.py
odoo_addons/email_template_qweb/static/description/icon.png
odoo_addons/email_template_qweb/tests/__init__.py
odoo_addons/email_template_qweb/tests/test_email_template_qweb.py
odoo_addons/email_template_qweb/views/email_template.xml
